herecobot/__init__.py
herecobot/__main__.py
herecobot/cli.py
herecobot/client.py
herecobot/exceptions.py
herecobot-0.2.0.dist-info/licenses/LICENSE
herecobot-0.2.0.dist-info/METADATA
herecobot-0.2.0.dist-info/WHEEL
herecobot-0.2.0.dist-info/entry_points.txt
herecobot-0.2.0.dist-info/top_level.txt
herecobot-0.2.0.dist-info/RECORD
