Metadata-Version: 2.4
Name: herecobot
Version: 0.2.0
Summary: Python SDK for HuggingFace Space AI models with OpenAI-style interface
Author-email: Shantanu Sen Gupta <shantanu@hereco.xyz>
License: MIT
Project-URL: Homepage, https://github.com/shntanuuhere/herecobot
Project-URL: Documentation, https://github.com/shntanuuhere/herecobot#readme
Project-URL: Repository, https://github.com/shntanuuhere/herecobot
Project-URL: Issues, https://github.com/shntanuuhere/herecobot/issues
Keywords: huggingface,chatbot,ai,gradio,herecobot
Classifier: Development Status :: 4 - Beta
Classifier: Intended Audience :: Developers
Classifier: License :: OSI Approved :: MIT License
Classifier: Programming Language :: Python :: 3
Classifier: Programming Language :: Python :: 3.8
Classifier: Programming Language :: Python :: 3.9
Classifier: Programming Language :: Python :: 3.10
Classifier: Programming Language :: Python :: 3.11
Classifier: Programming Language :: Python :: 3.12
Requires-Python: >=3.8
License-File: LICENSE
Requires-Dist: httpx>=0.24.0
Requires-Dist: gradio-client>=0.6.0
Provides-Extra: dev
Requires-Dist: pytest>=7.0.0; extra == "dev"
Requires-Dist: pytest-asyncio>=0.21.0; extra == "dev"
Requires-Dist: black>=23.0.0; extra == "dev"
Requires-Dist: ruff>=0.1.0; extra == "dev"
Dynamic: license-file
